musicvideos_youtube/__init__.py
musicvideos_youtube/upload.py
musicvideos_youtube-0.0.1.dist-info/LICENSE
musicvideos_youtube-0.0.1.dist-info/METADATA
musicvideos_youtube-0.0.1.dist-info/WHEEL
musicvideos_youtube-0.0.1.dist-info/top_level.txt
musicvideos_youtube-0.0.1.dist-info/RECORD
